MANIFEST.in
README
setup.py
oldowan/__init__.py
oldowan.mtdna.egg-info/PKG-INFO
oldowan.mtdna.egg-info/SOURCES.txt
oldowan.mtdna.egg-info/dependency_links.txt
oldowan.mtdna.egg-info/namespace_packages.txt
oldowan.mtdna.egg-info/not-zip-safe
oldowan.mtdna.egg-info/top_level.txt
oldowan/mtdna/VERSION
oldowan/mtdna/__init__.py
oldowan/mtdna/rCRS.py