Metadata-Version: 1.0
Name: oldowan.mtdna
Version: 1.0.3
Summary: Human reference mtdna sequence in Python formats.
